{
  "schema": {
    "id": "fertilizer",
    "version": "2025-09-V3e"
  },
  "id": "0FCC39",
  "metadata": {
    "registrant": "K + S NORTH AMERICA",
    "label_name": "K+S USA EPSO TOP \"FREE FLOW\" 0-0-0",
    "wsda_reg_no": "(#2278-0005)",
    "formulation": null,
    "first_seen": "2025-07-25",
    "detail_updated_at": "2025-07-25T11:15:37Z",
    "wsda_product_number": "(#2278-0005)",
    "legacy": {
      "schema_version": "2025-07-v1",
      "wsda_record": {
        "wsda_product_number": "(#2278-0005)",
        "product_name": "K+S USA EPSO TOP \"FREE FLOW\" 0-0-0",
        "company_info": {
          "company": "K + S NORTH AMERICA",
          "Mailing Address": "PO Box 6407",
          "Post Office Box": null,
          "City": "Aurora",
          "State": "IL",
          "Postal Code": "60598",
          "Telephone Number": "833 554-4401",
          "Fax Number": null
        },
        "guaranteed_analysis": {
          "Total Nitrogen (N)": null,
          "Available Phosphoric Acid (P2O5)": null,
          "Soluble Potash (K2O)": null,
          "Calcium (Ca)": null,
          "Magnesium (Mg)": 9.6,
          "Sulfur (S)": 13.0,
          "Boron (B)": null,
          "Chlorine (Cl)": null,
          "Cobalt (Co)": null,
          "Copper (Cu)": null,
          "Iron (Fe)": null,
          "Manganese (Mn)": null,
          "Molybdenum (Mo)": null,
          "Sodium (Na)": null,
          "Zinc (Zn)": null
        },
        "reported_metals": {
          "Arsenic": "=2.0000",
          "Cadmium": "=2.0000",
          "Cobalt": "=2.0000",
          "Mercury": "=0.0200",
          "Molybdenum": "=2.0000",
          "Nickel": "=2.0000",
          "Lead": "=2.0000",
          "Selenium": "=2.0000",
          "Zinc": "=2.0000"
        },
        "GYPSUM & LIMING MATERIALS": {
          "Calcium Carbonate (CaCO3)": null,
          "Calcium Carbonate Equivalent (CaCO3)": null,
          "Magnesium Carbonate (MgCO3)": null,
          "Calcium Sulfate (CaSO42H2O)": null
        },
        "waste_derived_fertilizer": "N",
        "micronutrient_fertilizer": "N"
      },
      "waste_derived_fertilizer": "N",
      "micronutrient_fertilizer": "N",
      "physicochemical": {
        "density_kg_per_l": null,
        "ph": {
          "min": null,
          "max": null
        },
        "ec_ms_cm": null
      },
      "commerce": {
        "sku_list": [],
        "price_history": []
      }
    }
  },
  "product": {
    "name": "K+S USA EPSO TOP \"FREE FLOW\" 0-0-0",
    "brand": "K + S NORTH AMERICA",
    "manufacturer": {
      "name": "K + S NORTH AMERICA"
    }
  },
  "composition": {
    "npk": {
      "basis": "oxide"
    },
    "macros_pct": {
      "Mg": 9.6,
      "S": 13.0
    },
    "heavy_metals": {
      "basis": "as_sold",
      "samples": [
        {
          "sample_id": "0FCC39-wsda",
          "date_utc": "2025-07-25T11:15:37Z",
          "basis": "as_sold",
          "results_ppm": {
            "As": 2.0,
            "Cd": 2.0,
            "Co": 2.0,
            "Hg": 0.02,
            "Mo": 2.0,
            "Ni": 2.0,
            "Pb": 2.0,
            "Se": 2.0,
            "Zn": 2.0
          },
          "qualifiers": {
            "As": "eq",
            "Cd": "eq",
            "Co": "eq",
            "Hg": "eq",
            "Mo": "eq",
            "Ni": "eq",
            "Pb": "eq",
            "Se": "eq",
            "Zn": "eq"
          }
        }
      ],
      "typical_ppm": {
        "As": 2.0,
        "Cd": 2.0,
        "Co": 2.0,
        "Hg": 0.02,
        "Mo": 2.0,
        "Ni": 2.0,
        "Pb": 2.0,
        "Se": 2.0,
        "Zn": 2.0
      }
    }
  }
}
