{"schema_version":"2025-07-v1","product_id":"22600A","source_wsda_record":{"wsda_product_number":"(#2229-0020)","product_name":"CUTTING EDGE SOLUTIONS LOUDER POWDER GROW B 8-13-31","company_info":{"company":"CUTTING EDGE SOLUTIONS LLC","Mailing Address":"PO Box 1727","Post Office Box":null,"City":"Santa Rosa","State":"CA","Postal Code":"95402","Telephone Number":"707 528-0522","Fax Number":null},"guaranteed_analysis":{"Total Nitrogen (N)":8.0,"Available Phosphoric Acid (P2O5)":13.0,"Soluble Potash (K2O)":31.0,"Calcium (Ca)":null,"Magnesium (Mg)":0.7,"Sulfur (S)":4.0,"Boron (B)":0.05,"Chlorine (Cl)":null,"Cobalt (Co)":null,"Copper (Cu)":null,"Iron (Fe)":0.2,"Manganese (Mn)":0.13,"Molybdenum (Mo)":null,"Sodium (Na)":null,"Zinc (Zn)":null},"reported_metals":{"Arsenic":"=1.3000","Cadmium":"=0.1000","Cobalt":"=0.1000","Mercury":"=0.0500","Molybdenum":"=46.0000","Nickel":"=0.9000","Lead":"=1.0000","Selenium":"=0.3000","Zinc":"=338.0000"},"GYPSUM & LIMING MATERIALS":{"Calcium Carbonate (CaCO3)":null,"Calcium Carbonate Equivalent (CaCO3)":null,"Magnesium Carbonate (MgCO3)":null,"Calcium Sulfate (CaSO42H2O)":null},"waste_derived_fertilizer":"N","micronutrient_fertilizer":"N"},"composition":{"guaranteed_analysis":{"Total Nitrogen (N)":8.0,"Available Phosphoric Acid (P2O5)":13.0,"Soluble Potash (K2O)":31.0,"Calcium (Ca)":null,"Magnesium (Mg)":0.7,"Sulfur (S)":4.0,"Boron (B)":0.05,"Chlorine (Cl)":null,"Cobalt (Co)":null,"Copper (Cu)":null,"Iron (Fe)":0.2,"Manganese (Mn)":0.13,"Molybdenum (Mo)":null,"Sodium (Na)":null,"Zinc (Zn)":null},"heavy_metals":{"Arsenic":"=1.3000","Cadmium":"=0.1000","Cobalt":"=0.1000","Mercury":"=0.0500","Molybdenum":"=46.0000","Nickel":"=0.9000","Lead":"=1.0000","Selenium":"=0.3000","Zinc":"=338.0000"},"derived_from_raw":null,"derived_from_tokens":null},"physicochemical":{"density_kg_per_l":null,"ph":{"min":null,"max":null},"ec_ms_cm":null},"commerce":{"sku_list":[],"price_history":[]},"metadata":{"registrant":"CUTTING EDGE SOLUTIONS LLC","label_name":"CUTTING EDGE SOLUTIONS LOUDER POWDER GROW B 8-13-31","wsda_reg_no":"(#2229-0020)","formulation":"Liquid","first_seen":"2025-07-25","detail_updated_at":"2025-07-25T11:15:37Z"}}
