{"schema_version":"2025-07-v1","product_id":"EFAB24","source_wsda_record":{"wsda_product_number":"(#2585-0002)","product_name":"REVIVE-PRO REVIVE-PRO 5-1-1","company_info":{"company":"REVIVE INC - U S GENERAL CORP","Mailing Address":"10473 Arapahoe Rd","Post Office Box":null,"City":"Layfayette","State":"CO","Postal Code":"80026","Telephone Number":"303 426-0373","Fax Number":null},"guaranteed_analysis":{"Total Nitrogen (N)":5.0,"Available Phosphoric Acid (P2O5)":1.0,"Soluble Potash (K2O)":1.0,"Calcium (Ca)":null,"Magnesium (Mg)":null,"Sulfur (S)":null,"Boron (B)":null,"Chlorine (Cl)":null,"Cobalt (Co)":null,"Copper (Cu)":null,"Iron (Fe)":2.0,"Manganese (Mn)":null,"Molybdenum (Mo)":null,"Sodium (Na)":null,"Zinc (Zn)":null},"reported_metals":{"Arsenic":"=9.6500","Cadmium":"=0.1000","Cobalt":"=3.6900","Mercury":"=0.1000","Molybdenum":"=2.5600","Nickel":"=4.9400","Lead":"=0.7000","Selenium":"=10.4600","Zinc":"=0.0300"},"GYPSUM & LIMING MATERIALS":{"Calcium Carbonate (CaCO3)":null,"Calcium Carbonate Equivalent (CaCO3)":null,"Magnesium Carbonate (MgCO3)":null,"Calcium Sulfate (CaSO42H2O)":null},"waste_derived_fertilizer":"N","micronutrient_fertilizer":"N"},"composition":{"guaranteed_analysis":{"Total Nitrogen (N)":5.0,"Available Phosphoric Acid (P2O5)":1.0,"Soluble Potash (K2O)":1.0,"Calcium (Ca)":null,"Magnesium (Mg)":null,"Sulfur (S)":null,"Boron (B)":null,"Chlorine (Cl)":null,"Cobalt (Co)":null,"Copper (Cu)":null,"Iron (Fe)":2.0,"Manganese (Mn)":null,"Molybdenum (Mo)":null,"Sodium (Na)":null,"Zinc (Zn)":null},"heavy_metals":{"Arsenic":"=9.6500","Cadmium":"=0.1000","Cobalt":"=3.6900","Mercury":"=0.1000","Molybdenum":"=2.5600","Nickel":"=4.9400","Lead":"=0.7000","Selenium":"=10.4600","Zinc":"=0.0300"},"derived_from_raw":null,"derived_from_tokens":null},"physicochemical":{"density_kg_per_l":null,"ph":{"min":null,"max":null},"ec_ms_cm":null},"commerce":{"sku_list":[],"price_history":[]},"metadata":{"registrant":"REVIVE INC - U S GENERAL CORP","label_name":"REVIVE-PRO REVIVE-PRO 5-1-1","wsda_reg_no":"(#2585-0002)","formulation":null,"first_seen":"2025-07-25","detail_updated_at":"2025-07-25T11:15:37Z"}}
