[
  {
    "wsda_product_number": "2285-0006",
    "product_name": "Intrepid Potash-New Mexico LLC Granular Potash 0-0-60 0-0-60",
    "guaranteed_analysis": {
      "Total Nitrogen (N)": 0.0,
      "Available Phosphoric Acid (P2O5)": 0.0,
      "Soluble Potash (K2O)": 60.0,
      "Calcium (Ca)": null,
      "Magnesium (Mg)": null,
      "Sulfur (S)": null,
      "Boron (B)": null,
      "Chlorine (Cl)": null,
      "Cobalt (Co)": null,
      "Copper (Cu)": null,
      "Iron (Fe)": null,
      "Manganese (Mn)": null,
      "Molybdenum (Mo)": null,
      "Sodium (Na)": null,
      "Zinc (Zn)": null
    },
    "reported_metals": {
      "Arsenic": "<0.5000",
      "Cadmium": "<0.1000",
      "Cobalt": "<0.1000",
      "Mercury": "<0.0020",
      "Molybdenum": "<0.5000",
      "Nickel": "=0.5000",
      "Lead": "=0.3000",
      "Selenium": "<0.0500",
      "Zinc": "=0.6000"
    },
    "waste_derived_fertilizer": "N",
    "micronutrient_fertilizer": "N",
    "company": "Intrepid Potash - New Mexico LLC"
  },
  {
    "wsda_product_number": "4083-0001",
    "product_name": "1st Choice Fertilizer Earth-Care Plus 5-6-6",
    "guaranteed_analysis": {
      "Total Nitrogen (N)": 5.0,
      "Available Phosphoric Acid (P2O5)": 6.0,
      "Soluble Potash (K2O)": 6.0,
      "Calcium (Ca)": null,
      "Magnesium (Mg)": null,
      "Sulfur (S)": null,
      "Boron (B)": null,
      "Chlorine (Cl)": null,
      "Cobalt (Co)": null,
      "Copper (Cu)": null,
      "Iron (Fe)": null,
      "Manganese (Mn)": null,
      "Molybdenum (Mo)": null,
      "Sodium (Na)": null,
      "Zinc (Zn)": null
    },
    "reported_metals": {
      "Arsenic": "<0.2500",
      "Cadmium": "=0.1000",
      "Cobalt": "=0.4000",
      "Mercury": "<0.0500",
      "Molybdenum": "=1.1000",
      "Nickel": "=3.6000",
      "Lead": "=0.7000",
      "Selenium": "=0.8000",
      "Zinc": "=293.9000"
    },
    "waste_derived_fertilizer": "N",
    "micronutrient_fertilizer": "N",
    "company": "1st Choice Fertilizer, Inc"
  },
  {
    "wsda_product_number": "3830-0001",
    "product_name": "20 Mule Team Borax Fertibor Sodium Borate 15% B 0-0-0",
    "guaranteed_analysis": {
      "Total Nitrogen (N)": 0.0,
      "Available Phosphoric Acid (P2O5)": 0.0,
      "Soluble Potash (K2O)": 0.0,
      "Calcium (Ca)": null,
      "Magnesium (Mg)": null,
      "Sulfur (S)": null,
      "Boron (B)": 15.0,
      "Chlorine (Cl)": null,
      "Cobalt (Co)": null,
      "Copper (Cu)": null,
      "Iron (Fe)": null,
      "Manganese (Mn)": null,
      "Molybdenum (Mo)": null,
      "Sodium (Na)": null,
      "Zinc (Zn)": null
    },
    "reported_metals": {
      "Arsenic": "=3.0000",
      "Cadmium": "<1.0000",
      "Cobalt": "<1.0000",
      "Mercury": "<0.0500",
      "Molybdenum": "<1.0000",
      "Nickel": "<1.0000",
      "Lead": "<1.0000",
      "Selenium": "<2.5000",
      "Zinc": "<1.0000"
    },
    "waste_derived_fertilizer": "Y",
    "micronutrient_fertilizer": "N",
    "company": "US Borax"
  },
  {
    "wsda_product_number": "3830-0003",
    "product_name": "20 Mule Team Borax Granubor Sodium Borate 15% B 0-0-0",
    "guaranteed_analysis": {
      "Total Nitrogen (N)": 0.0,
      "Available Phosphoric Acid (P2O5)": 0.0,
      "Soluble Potash (K2O)": 0.0,
      "Calcium (Ca)": null,
      "Magnesium (Mg)": null,
      "Sulfur (S)": null,
      "Boron (B)": 17.5,
      "Chlorine (Cl)": null,
      "Cobalt (Co)": null,
      "Copper (Cu)": null,
      "Iron (Fe)": null,
      "Manganese (Mn)": null,
      "Molybdenum (Mo)": null,
      "Sodium (Na)": null,
      "Zinc (Zn)": null
    },
    "reported_metals": {
      "Arsenic": "<0.0250",
      "Cadmium": "<0.0250",
      "Cobalt": "<0.0100",
      "Mercury": "<0.0010",
      "Molybdenum": "<0.0500",
      "Nickel": "<0.0500",
      "Lead": "<0.0250",
      "Selenium": "<0.0250",
      "Zinc": "<0.1000"
    },
    "waste_derived_fertilizer": "N",
    "micronutrient_fertilizer": "Y",
    "company": "US Borax"
  },
  {
    "wsda_product_number": "0001-0025",
    "product_name": "Acadian Liquid Seaweed Concentrate 0-0-5",
    "guaranteed_analysis": {
      "Total Nitrogen (N)": 0.0,
      "Available Phosphoric Acid (P2O5)": 0.0,
      "Soluble Potash (K2O)": 5.0,
      "Calcium (Ca)": null,
      "Magnesium (Mg)": null,
      "Sulfur (S)": null,
      "Boron (B)": null,
      "Chlorine (Cl)": null,
      "Cobalt (Co)": null,
      "Copper (Cu)": null,
      "Iron (Fe)": null,
      "Manganese (Mn)": null,
      "Molybdenum (Mo)": null,
      "Sodium (Na)": null,
      "Zinc (Zn)": null
    },
    "reported_metals": {
      "Arsenic": "<0.5000",
      "Cadmium": "<0.5000",
      "Cobalt": "<0.5000",
      "Mercury": "<0.0020",
      "Molybdenum": "<0.5000",
      "Nickel": "<0.5000",
      "Lead": "=1.2100",
      "Selenium": "<0.5000",
      "Zinc": "=2.5200"
    },
    "waste_derived_fertilizer": "N",
    "micronutrient_fertilizer": "N",
    "company": "Montana Sulphur & Chemical Co"
  }
]
