{
  "schema": {
    "id": "fertilizer",
    "version": "2025-09-V3e"
  },
  "id": "775370",
  "metadata": {
    "registrant": "WILBUR ELLIS COMPANY LLC",
    "label_name": "FOLI-GRO ACTION 2-17-17",
    "wsda_reg_no": "(#0349-0397)",
    "formulation": null,
    "first_seen": "2025-07-25",
    "detail_updated_at": "2025-07-25T11:15:37Z",
    "wsda_product_number": "(#0349-0397)",
    "legacy": {
      "schema_version": "2025-07-v1",
      "wsda_record": {
        "wsda_product_number": "(#0349-0397)",
        "product_name": "FOLI-GRO ACTION 2-17-17",
        "company_info": {
          "company": "WILBUR ELLIS COMPANY LLC",
          "Mailing Address": "4582 S. Ulster Street Parkway",
          "Post Office Box": null,
          "City": "Denver",
          "State": "CO",
          "Postal Code": "80237",
          "Telephone Number": "802 236-3745",
          "Fax Number": null
        },
        "guaranteed_analysis": {
          "Total Nitrogen (N)": 2.0,
          "Available Phosphoric Acid (P2O5)": 17.0,
          "Soluble Potash (K2O)": 17.0,
          "Calcium (Ca)": null,
          "Magnesium (Mg)": null,
          "Sulfur (S)": null,
          "Boron (B)": null,
          "Chlorine (Cl)": null,
          "Cobalt (Co)": null,
          "Copper (Cu)": null,
          "Iron (Fe)": 0.1,
          "Manganese (Mn)": 0.08,
          "Molybdenum (Mo)": 0.005,
          "Sodium (Na)": null,
          "Zinc (Zn)": 0.15
        },
        "reported_metals": {
          "Arsenic": "<5.0000",
          "Cadmium": "<0.4000",
          "Cobalt": "<1.0000",
          "Mercury": "<0.0050",
          "Molybdenum": "<2.0000",
          "Nickel": "<3.0000",
          "Lead": "<3.0000",
          "Selenium": "<5.0000",
          "Zinc": "=1460.0000"
        },
        "GYPSUM & LIMING MATERIALS": {
          "Calcium Carbonate (CaCO3)": null,
          "Calcium Carbonate Equivalent (CaCO3)": null,
          "Magnesium Carbonate (MgCO3)": null,
          "Calcium Sulfate (CaSO42H2O)": null
        },
        "waste_derived_fertilizer": "N",
        "micronutrient_fertilizer": "N"
      },
      "waste_derived_fertilizer": "N",
      "micronutrient_fertilizer": "N",
      "physicochemical": {
        "density_kg_per_l": null,
        "ph": {
          "min": null,
          "max": null
        },
        "ec_ms_cm": null
      },
      "commerce": {
        "sku_list": [],
        "price_history": []
      }
    }
  },
  "product": {
    "name": "FOLI-GRO ACTION 2-17-17",
    "brand": "WILBUR ELLIS COMPANY LLC",
    "manufacturer": {
      "name": "WILBUR ELLIS COMPANY LLC"
    }
  },
  "composition": {
    "npk": {
      "basis": "oxide",
      "N_pct": 2.0,
      "P2O5_pct": 17.0,
      "K2O_pct": 17.0
    },
    "micros_pct": {
      "Fe": 0.1,
      "Mn": 0.08,
      "Zn": 0.15,
      "Mo": 0.005
    },
    "heavy_metals": {
      "basis": "as_sold",
      "samples": [
        {
          "sample_id": "775370-wsda",
          "date_utc": "2025-07-25T11:15:37Z",
          "basis": "as_sold",
          "results_ppm": {
            "As": 5.0,
            "Cd": 0.4,
            "Co": 1.0,
            "Hg": 0.005,
            "Mo": 2.0,
            "Ni": 3.0,
            "Pb": 3.0,
            "Se": 5.0,
            "Zn": 1460.0
          },
          "detection_limits_ppm": {
            "As": 5.0,
            "Cd": 0.4,
            "Co": 1.0,
            "Hg": 0.005,
            "Mo": 2.0,
            "Ni": 3.0,
            "Pb": 3.0,
            "Se": 5.0
          },
          "qualifiers": {
            "As": "lt_dl",
            "Cd": "lt_dl",
            "Co": "lt_dl",
            "Hg": "lt_dl",
            "Mo": "lt_dl",
            "Ni": "lt_dl",
            "Pb": "lt_dl",
            "Se": "lt_dl",
            "Zn": "eq"
          }
        }
      ],
      "typical_ppm": {
        "Zn": 1460.0
      }
    }
  }
}
