{
  "schema": {
    "id": "fertilizer",
    "version": "2025-09-V3e"
  },
  "id": "903DE7",
  "metadata": {
    "registrant": "SCOTTS COMPANY (THE)",
    "label_name": "OSMOCOTE SMART-RELEASE PLANT FOOD FLOWER & VEGETABLES PLANT FOOD 14-14-14",
    "wsda_reg_no": "(#0236-0578)",
    "formulation": null,
    "first_seen": "2025-07-25",
    "detail_updated_at": "2025-07-25T11:15:37Z",
    "wsda_product_number": "(#0236-0578)",
    "legacy": {
      "schema_version": "2025-07-v1",
      "wsda_record": {
        "wsda_product_number": "(#0236-0578)",
        "product_name": "OSMOCOTE SMART-RELEASE PLANT FOOD FLOWER & VEGETABLES PLANT FOOD 14-14-14",
        "company_info": {
          "company": "SCOTTS COMPANY (THE)",
          "Mailing Address": "14111 Scottslawn Rd",
          "Post Office Box": null,
          "City": "Marysville",
          "State": "OH",
          "Postal Code": "43041",
          "Telephone Number": "937 645-2523",
          "Fax Number": null
        },
        "guaranteed_analysis": {
          "Total Nitrogen (N)": 14.0,
          "Available Phosphoric Acid (P2O5)": 14.0,
          "Soluble Potash (K2O)": 14.0,
          "Calcium (Ca)": null,
          "Magnesium (Mg)": null,
          "Sulfur (S)": null,
          "Boron (B)": null,
          "Chlorine (Cl)": null,
          "Cobalt (Co)": null,
          "Copper (Cu)": null,
          "Iron (Fe)": null,
          "Manganese (Mn)": null,
          "Molybdenum (Mo)": null,
          "Sodium (Na)": null,
          "Zinc (Zn)": null
        },
        "reported_metals": {
          "Arsenic": "=1.5600",
          "Cadmium": "=1.7700",
          "Cobalt": "=23.7000",
          "Mercury": "=0.0084",
          "Molybdenum": "=1.2200",
          "Nickel": "=4.9300",
          "Lead": "=1.6200",
          "Selenium": "=2.7400",
          "Zinc": "=34.6000"
        },
        "GYPSUM & LIMING MATERIALS": {
          "Calcium Carbonate (CaCO3)": null,
          "Calcium Carbonate Equivalent (CaCO3)": null,
          "Magnesium Carbonate (MgCO3)": null,
          "Calcium Sulfate (CaSO42H2O)": null
        },
        "waste_derived_fertilizer": "N",
        "micronutrient_fertilizer": "N"
      },
      "waste_derived_fertilizer": "N",
      "micronutrient_fertilizer": "N",
      "physicochemical": {
        "density_kg_per_l": null,
        "ph": {
          "min": null,
          "max": null
        },
        "ec_ms_cm": null
      },
      "commerce": {
        "sku_list": [],
        "price_history": []
      }
    }
  },
  "product": {
    "name": "OSMOCOTE SMART-RELEASE PLANT FOOD FLOWER & VEGETABLES PLANT FOOD 14-14-14",
    "brand": "SCOTTS COMPANY (THE)",
    "manufacturer": {
      "name": "SCOTTS COMPANY (THE)"
    }
  },
  "composition": {
    "npk": {
      "basis": "oxide",
      "N_pct": 14.0,
      "P2O5_pct": 14.0,
      "K2O_pct": 14.0
    },
    "heavy_metals": {
      "basis": "as_sold",
      "samples": [
        {
          "sample_id": "903DE7-wsda",
          "date_utc": "2025-07-25T11:15:37Z",
          "basis": "as_sold",
          "results_ppm": {
            "As": 1.56,
            "Cd": 1.77,
            "Co": 23.7,
            "Hg": 0.0084,
            "Mo": 1.22,
            "Ni": 4.93,
            "Pb": 1.62,
            "Se": 2.74,
            "Zn": 34.6
          },
          "qualifiers": {
            "As": "eq",
            "Cd": "eq",
            "Co": "eq",
            "Hg": "eq",
            "Mo": "eq",
            "Ni": "eq",
            "Pb": "eq",
            "Se": "eq",
            "Zn": "eq"
          }
        }
      ],
      "typical_ppm": {
        "As": 1.56,
        "Cd": 1.77,
        "Co": 23.7,
        "Hg": 0.0084,
        "Mo": 1.22,
        "Ni": 4.93,
        "Pb": 1.62,
        "Se": 2.74,
        "Zn": 34.6
      }
    }
  }
}
