{
  "schema": {
    "id": "fertilizer",
    "version": "2025-09-V3e"
  },
  "id": "A14619",
  "metadata": {
    "registrant": "BAICOR LC",
    "label_name": "PHYTO-PLUS ZINC 5% 0-0-0",
    "wsda_reg_no": "(#0411-0060)",
    "formulation": null,
    "first_seen": "2025-07-25",
    "detail_updated_at": "2025-07-25T11:15:37Z",
    "wsda_product_number": "(#0411-0060)",
    "legacy": {
      "schema_version": "2025-07-v1",
      "wsda_record": {
        "wsda_product_number": "(#0411-0060)",
        "product_name": "PHYTO-PLUS ZINC 5% 0-0-0",
        "company_info": {
          "company": "BAICOR LC",
          "Mailing Address": "PO Box 725",
          "Post Office Box": null,
          "City": ":Logan",
          "State": "UT",
          "Postal Code": "84323-0725",
          "Telephone Number": "435 752-2475",
          "Fax Number": null
        },
        "guaranteed_analysis": {
          "Total Nitrogen (N)": null,
          "Available Phosphoric Acid (P2O5)": null,
          "Soluble Potash (K2O)": null,
          "Calcium (Ca)": null,
          "Magnesium (Mg)": null,
          "Sulfur (S)": null,
          "Boron (B)": null,
          "Chlorine (Cl)": null,
          "Cobalt (Co)": null,
          "Copper (Cu)": null,
          "Iron (Fe)": null,
          "Manganese (Mn)": null,
          "Molybdenum (Mo)": null,
          "Sodium (Na)": null,
          "Zinc (Zn)": 5.0
        },
        "reported_metals": {
          "Arsenic": "<0.3000",
          "Cadmium": "<0.1000",
          "Cobalt": "=4.5000",
          "Mercury": "<0.0100",
          "Molybdenum": "<0.1000",
          "Nickel": "=10.7000",
          "Lead": "<0.5000",
          "Selenium": "<0.8000",
          "Zinc": "=55100.0000"
        },
        "GYPSUM & LIMING MATERIALS": {
          "Calcium Carbonate (CaCO3)": null,
          "Calcium Carbonate Equivalent (CaCO3)": null,
          "Magnesium Carbonate (MgCO3)": null,
          "Calcium Sulfate (CaSO42H2O)": null
        },
        "waste_derived_fertilizer": "N",
        "micronutrient_fertilizer": "Y"
      },
      "waste_derived_fertilizer": "N",
      "micronutrient_fertilizer": "Y",
      "physicochemical": {
        "density_kg_per_l": null,
        "ph": {
          "min": null,
          "max": null
        },
        "ec_ms_cm": null
      },
      "commerce": {
        "sku_list": [],
        "price_history": []
      }
    }
  },
  "product": {
    "name": "PHYTO-PLUS ZINC 5% 0-0-0",
    "brand": "BAICOR LC",
    "manufacturer": {
      "name": "BAICOR LC"
    }
  },
  "composition": {
    "npk": {
      "basis": "oxide"
    },
    "micros_pct": {
      "Zn": 5.0
    },
    "heavy_metals": {
      "basis": "as_sold",
      "samples": [
        {
          "sample_id": "A14619-wsda",
          "date_utc": "2025-07-25T11:15:37Z",
          "basis": "as_sold",
          "results_ppm": {
            "As": 0.3,
            "Cd": 0.1,
            "Co": 4.5,
            "Hg": 0.01,
            "Mo": 0.1,
            "Ni": 10.7,
            "Pb": 0.5,
            "Se": 0.8,
            "Zn": 55100.0
          },
          "detection_limits_ppm": {
            "As": 0.3,
            "Cd": 0.1,
            "Hg": 0.01,
            "Mo": 0.1,
            "Pb": 0.5,
            "Se": 0.8
          },
          "qualifiers": {
            "As": "lt_dl",
            "Cd": "lt_dl",
            "Co": "eq",
            "Hg": "lt_dl",
            "Mo": "lt_dl",
            "Ni": "eq",
            "Pb": "lt_dl",
            "Se": "lt_dl",
            "Zn": "eq"
          }
        }
      ],
      "typical_ppm": {
        "Co": 4.5,
        "Ni": 10.7,
        "Zn": 55100.0
      }
    }
  }
}
