{"schema_version":"2025-07-v1","product_id":"C265FD","source_wsda_record":{"wsda_product_number":"(#0989-0074)","product_name":"KNOX FERTILIZER COMPANY SHAW'S TURF FOOD WITH DIMENSION 170 23-0-8","company_info":{"company":"KNOX FERTILIZER COMPANY INC","Mailing Address":"PO Box 248","Post Office Box":null,"City":"Knox","State":"IN","Postal Code":"46534","Telephone Number":"574 772-6278","Fax Number":null},"guaranteed_analysis":{"Total Nitrogen (N)":23.0,"Available Phosphoric Acid (P2O5)":null,"Soluble Potash (K2O)":8.0,"Calcium (Ca)":null,"Magnesium (Mg)":null,"Sulfur (S)":null,"Boron (B)":null,"Chlorine (Cl)":null,"Cobalt (Co)":null,"Copper (Cu)":null,"Iron (Fe)":null,"Manganese (Mn)":null,"Molybdenum (Mo)":null,"Sodium (Na)":null,"Zinc (Zn)":null},"reported_metals":{"Arsenic":"=0.4220","Cadmium":"<0.0050","Cobalt":"=0.3900","Mercury":"<0.0027","Molybdenum":"=0.1670","Nickel":"=0.9570","Lead":"=0.3640","Selenium":"=3.0500","Zinc":"=2.0700"},"GYPSUM & LIMING MATERIALS":{"Calcium Carbonate (CaCO3)":null,"Calcium Carbonate Equivalent (CaCO3)":null,"Magnesium Carbonate (MgCO3)":null,"Calcium Sulfate (CaSO42H2O)":null},"waste_derived_fertilizer":"N","micronutrient_fertilizer":"N"},"composition":{"guaranteed_analysis":{"Total Nitrogen (N)":23.0,"Available Phosphoric Acid (P2O5)":null,"Soluble Potash (K2O)":8.0,"Calcium (Ca)":null,"Magnesium (Mg)":null,"Sulfur (S)":null,"Boron (B)":null,"Chlorine (Cl)":null,"Cobalt (Co)":null,"Copper (Cu)":null,"Iron (Fe)":null,"Manganese (Mn)":null,"Molybdenum (Mo)":null,"Sodium (Na)":null,"Zinc (Zn)":null},"heavy_metals":{"Arsenic":"=0.4220","Cadmium":"<0.0050","Cobalt":"=0.3900","Mercury":"<0.0027","Molybdenum":"=0.1670","Nickel":"=0.9570","Lead":"=0.3640","Selenium":"=3.0500","Zinc":"=2.0700"},"derived_from_raw":null,"derived_from_tokens":null},"physicochemical":{"density_kg_per_l":null,"ph":{"min":null,"max":null},"ec_ms_cm":null},"commerce":{"sku_list":[],"price_history":[]},"metadata":{"registrant":"KNOX FERTILIZER COMPANY INC","label_name":"KNOX FERTILIZER COMPANY SHAW'S TURF FOOD WITH DIMENSION 170 23-0-8","wsda_reg_no":"(#0989-0074)","formulation":null,"first_seen":"2025-07-25","detail_updated_at":"2025-07-25T11:15:37Z"}}