{
  "schema": {
    "id": "fertilizer",
    "version": "2025-09-V3e"
  },
  "id": "4E4DA1",
  "metadata": {
    "registrant": "TPS NUTRIENTS INC",
    "label_name": "TPS PLANT FOOD SIMPLE FEED FORMULA: CHRISTMAS CACTUS FERTILIZER 2-2-3",
    "wsda_reg_no": "(#3536-0041)",
    "formulation": null,
    "first_seen": "2025-07-25",
    "detail_updated_at": "2025-07-25T11:15:37Z",
    "wsda_product_number": "(#3536-0041)",
    "legacy": {
      "schema_version": "2025-07-v1",
      "wsda_record": {
        "wsda_product_number": "(#3536-0041)",
        "product_name": "TPS PLANT FOOD SIMPLE FEED FORMULA: CHRISTMAS CACTUS FERTILIZER 2-2-3",
        "company_info": {
          "company": "TPS NUTRIENTS INC",
          "Mailing Address": "PO Box 875",
          "Post Office Box": null,
          "City": "Bellevue",
          "State": "WA",
          "Postal Code": "98009",
          "Telephone Number": "425 765-8460",
          "Fax Number": null
        },
        "guaranteed_analysis": {
          "Total Nitrogen (N)": 2.0,
          "Available Phosphoric Acid (P2O5)": 2.0,
          "Soluble Potash (K2O)": 3.0,
          "Calcium (Ca)": 1.0,
          "Magnesium (Mg)": 0.5,
          "Sulfur (S)": null,
          "Boron (B)": 0.02,
          "Chlorine (Cl)": null,
          "Cobalt (Co)": null,
          "Copper (Cu)": 0.05,
          "Iron (Fe)": 0.1,
          "Manganese (Mn)": 0.05,
          "Molybdenum (Mo)": null,
          "Sodium (Na)": null,
          "Zinc (Zn)": 0.05
        },
        "reported_metals": {
          "Arsenic": "=0.1400",
          "Cadmium": "=0.0310",
          "Cobalt": "=0.0580",
          "Mercury": "<0.0027",
          "Molybdenum": "<0.0100",
          "Nickel": "<0.0200",
          "Lead": "=0.1300",
          "Selenium": "=0.0910",
          "Zinc": "=67.8000"
        },
        "GYPSUM & LIMING MATERIALS": {
          "Calcium Carbonate (CaCO3)": null,
          "Calcium Carbonate Equivalent (CaCO3)": null,
          "Magnesium Carbonate (MgCO3)": null,
          "Calcium Sulfate (CaSO42H2O)": null
        },
        "waste_derived_fertilizer": "N",
        "micronutrient_fertilizer": "N"
      },
      "waste_derived_fertilizer": "N",
      "micronutrient_fertilizer": "N",
      "physicochemical": {
        "density_kg_per_l": null,
        "ph": {
          "min": null,
          "max": null
        },
        "ec_ms_cm": null
      },
      "commerce": {
        "sku_list": [],
        "price_history": []
      }
    }
  },
  "product": {
    "name": "TPS PLANT FOOD SIMPLE FEED FORMULA: CHRISTMAS CACTUS FERTILIZER 2-2-3",
    "brand": "TPS NUTRIENTS INC",
    "manufacturer": {
      "name": "TPS NUTRIENTS INC"
    }
  },
  "composition": {
    "npk": {
      "basis": "oxide",
      "N_pct": 2.0,
      "P2O5_pct": 2.0,
      "K2O_pct": 3.0
    },
    "macros_pct": {
      "Ca": 1.0,
      "Mg": 0.5
    },
    "micros_pct": {
      "Fe": 0.1,
      "Mn": 0.05,
      "Zn": 0.05,
      "Cu": 0.05,
      "B": 0.02
    },
    "heavy_metals": {
      "basis": "as_sold",
      "samples": [
        {
          "sample_id": "4E4DA1-wsda",
          "date_utc": "2025-07-25T11:15:37Z",
          "basis": "as_sold",
          "results_ppm": {
            "As": 0.14,
            "Cd": 0.031,
            "Co": 0.058,
            "Hg": 0.0027,
            "Mo": 0.01,
            "Ni": 0.02,
            "Pb": 0.13,
            "Se": 0.091,
            "Zn": 67.8
          },
          "detection_limits_ppm": {
            "Hg": 0.0027,
            "Mo": 0.01,
            "Ni": 0.02
          },
          "qualifiers": {
            "As": "eq",
            "Cd": "eq",
            "Co": "eq",
            "Hg": "lt_dl",
            "Mo": "lt_dl",
            "Ni": "lt_dl",
            "Pb": "eq",
            "Se": "eq",
            "Zn": "eq"
          }
        }
      ],
      "typical_ppm": {
        "As": 0.14,
        "Cd": 0.031,
        "Co": 0.058,
        "Pb": 0.13,
        "Se": 0.091,
        "Zn": 67.8
      }
    }
  }
}
