{"schema_version":"2025-07-v1","product_id":"04DE57","source_wsda_record":{"wsda_product_number":"(#2055-0010)","product_name":"IONIC BLOOM FOR SOIL 2-2-5","company_info":{"company":"HYDRODYNAMICS INTERNATIONAL INC","Mailing Address":"3774 Indian Paintbrush Lane","Post Office Box":null,"City":"Island Park","State":"ID","Postal Code":"83429","Telephone Number":"559 313-9456","Fax Number":null},"guaranteed_analysis":{"Total Nitrogen (N)":2.0,"Available Phosphoric Acid (P2O5)":2.0,"Soluble Potash (K2O)":5.0,"Calcium (Ca)":null,"Magnesium (Mg)":null,"Sulfur (S)":null,"Boron (B)":null,"Chlorine (Cl)":null,"Cobalt (Co)":null,"Copper (Cu)":null,"Iron (Fe)":null,"Manganese (Mn)":null,"Molybdenum (Mo)":null,"Sodium (Na)":null,"Zinc (Zn)":null},"reported_metals":{"Arsenic":"=0.9000","Cadmium":"<0.1000","Cobalt":"<0.1000","Mercury":"<0.0100","Molybdenum":"=8.8000","Nickel":"=0.2000","Lead":"<0.7000","Selenium":"=0.3000","Zinc":"=51.0000"},"GYPSUM & LIMING MATERIALS":{"Calcium Carbonate (CaCO3)":null,"Calcium Carbonate Equivalent (CaCO3)":null,"Magnesium Carbonate (MgCO3)":null,"Calcium Sulfate (CaSO42H2O)":null},"waste_derived_fertilizer":"N","micronutrient_fertilizer":"N"},"composition":{"guaranteed_analysis":{"Total Nitrogen (N)":2.0,"Available Phosphoric Acid (P2O5)":2.0,"Soluble Potash (K2O)":5.0,"Calcium (Ca)":null,"Magnesium (Mg)":null,"Sulfur (S)":null,"Boron (B)":null,"Chlorine (Cl)":null,"Cobalt (Co)":null,"Copper (Cu)":null,"Iron (Fe)":null,"Manganese (Mn)":null,"Molybdenum (Mo)":null,"Sodium (Na)":null,"Zinc (Zn)":null},"heavy_metals":{"Arsenic":"=0.9000","Cadmium":"<0.1000","Cobalt":"<0.1000","Mercury":"<0.0100","Molybdenum":"=8.8000","Nickel":"=0.2000","Lead":"<0.7000","Selenium":"=0.3000","Zinc":"=51.0000"},"derived_from_raw":null,"derived_from_tokens":null},"physicochemical":{"density_kg_per_l":null,"ph":{"min":null,"max":null},"ec_ms_cm":null},"commerce":{"sku_list":[],"price_history":[]},"metadata":{"registrant":"HYDRODYNAMICS INTERNATIONAL INC","label_name":"IONIC BLOOM FOR SOIL 2-2-5","wsda_reg_no":"(#2055-0010)","formulation":null,"first_seen":"2025-07-25","detail_updated_at":"2025-07-25T11:15:37Z"}}
