{
  "schema": {
    "id": "fertilizer",
    "version": "2025-09-V3e"
  },
  "id": "FF74C4",
  "metadata": {
    "registrant": "EVERRIS NA INC",
    "label_name": "OSMOCOTE BLEND 17-5-11 8-9M 17-5-11",
    "wsda_reg_no": "(#2319-0187)",
    "formulation": null,
    "first_seen": "2025-07-25",
    "detail_updated_at": "2025-07-25T11:15:37Z",
    "wsda_product_number": "(#2319-0187)",
    "legacy": {
      "schema_version": "2025-07-v1",
      "wsda_record": {
        "wsda_product_number": "(#2319-0187)",
        "product_name": "OSMOCOTE BLEND 17-5-11 8-9M 17-5-11",
        "company_info": {
          "company": "EVERRIS NA INC",
          "Mailing Address": "PO Box 3310",
          "Post Office Box": null,
          "City": "Dublin",
          "State": "OH",
          "Postal Code": "43016",
          "Telephone Number": "314 983-7500",
          "Fax Number": null
        },
        "guaranteed_analysis": {
          "Total Nitrogen (N)": 17.0,
          "Available Phosphoric Acid (P2O5)": 5.0,
          "Soluble Potash (K2O)": 11.0,
          "Calcium (Ca)": 2.2,
          "Magnesium (Mg)": null,
          "Sulfur (S)": 5.7,
          "Boron (B)": null,
          "Chlorine (Cl)": null,
          "Cobalt (Co)": null,
          "Copper (Cu)": 0.13,
          "Iron (Fe)": 2.21,
          "Manganese (Mn)": 0.32,
          "Molybdenum (Mo)": 0.006,
          "Sodium (Na)": null,
          "Zinc (Zn)": 0.13
        },
        "reported_metals": {
          "Arsenic": "=0.7580",
          "Cadmium": "=0.4070",
          "Cobalt": "=113.0000",
          "Mercury": "=0.0194",
          "Molybdenum": "=115.0000",
          "Nickel": "=12.2000",
          "Lead": "=1.5800",
          "Selenium": "=1.2300",
          "Zinc": "=2060.0000"
        },
        "GYPSUM & LIMING MATERIALS": {
          "Calcium Carbonate (CaCO3)": null,
          "Calcium Carbonate Equivalent (CaCO3)": null,
          "Magnesium Carbonate (MgCO3)": "0.1000",
          "Calcium Sulfate (CaSO42H2O)": null
        },
        "waste_derived_fertilizer": "N",
        "micronutrient_fertilizer": "N"
      },
      "waste_derived_fertilizer": "N",
      "micronutrient_fertilizer": "N",
      "physicochemical": {
        "density_kg_per_l": null,
        "ph": {
          "min": null,
          "max": null
        },
        "ec_ms_cm": null
      },
      "commerce": {
        "sku_list": [],
        "price_history": []
      }
    }
  },
  "product": {
    "name": "OSMOCOTE BLEND 17-5-11 8-9M 17-5-11",
    "brand": "EVERRIS NA INC",
    "manufacturer": {
      "name": "EVERRIS NA INC"
    }
  },
  "composition": {
    "npk": {
      "basis": "oxide",
      "N_pct": 17.0,
      "P2O5_pct": 5.0,
      "K2O_pct": 11.0
    },
    "macros_pct": {
      "Ca": 2.2,
      "S": 5.7
    },
    "micros_pct": {
      "Fe": 2.21,
      "Mn": 0.32,
      "Zn": 0.13,
      "Cu": 0.13,
      "Mo": 0.006
    },
    "heavy_metals": {
      "basis": "as_sold",
      "samples": [
        {
          "sample_id": "FF74C4-wsda",
          "date_utc": "2025-07-25T11:15:37Z",
          "basis": "as_sold",
          "results_ppm": {
            "As": 0.758,
            "Cd": 0.407,
            "Co": 113.0,
            "Hg": 0.0194,
            "Mo": 115.0,
            "Ni": 12.2,
            "Pb": 1.58,
            "Se": 1.23,
            "Zn": 2060.0
          },
          "qualifiers": {
            "As": "eq",
            "Cd": "eq",
            "Co": "eq",
            "Hg": "eq",
            "Mo": "eq",
            "Ni": "eq",
            "Pb": "eq",
            "Se": "eq",
            "Zn": "eq"
          }
        }
      ],
      "typical_ppm": {
        "As": 0.758,
        "Cd": 0.407,
        "Co": 113.0,
        "Hg": 0.0194,
        "Mo": 115.0,
        "Ni": 12.2,
        "Pb": 1.58,
        "Se": 1.23,
        "Zn": 2060.0
      }
    }
  }
}
