{"schema_version":"2025-07-v1","product_id":"94617E","source_wsda_record":{"wsda_product_number":"(#1026-0015)","product_name":"PERFECT BLEND ORGANICS BIOTIC 8-4-5 SGN 150 8-4-5","company_info":{"company":"PERFECT BLEND LLC","Mailing Address":"10900 NE 8th St Ste 615","Post Office Box":null,"City":"Bellevue","State":"WA","Postal Code":"98004","Telephone Number":"425 456-8889","Fax Number":null},"guaranteed_analysis":{"Total Nitrogen (N)":8.0,"Available Phosphoric Acid (P2O5)":4.0,"Soluble Potash (K2O)":5.0,"Calcium (Ca)":7.0,"Magnesium (Mg)":0.7,"Sulfur (S)":3.0,"Boron (B)":0.02,"Chlorine (Cl)":null,"Cobalt (Co)":0.0005,"Copper (Cu)":0.05,"Iron (Fe)":0.1,"Manganese (Mn)":0.05,"Molybdenum (Mo)":0.0005,"Sodium (Na)":null,"Zinc (Zn)":0.05},"reported_metals":{"Arsenic":"=5.0000","Cadmium":"=5.0000","Cobalt":"=10.0000","Mercury":"=1.0000","Molybdenum":"=10.0000","Nickel":"=15.0000","Lead":"=15.0000","Selenium":"=6.4700","Zinc":"=1000.0000"},"GYPSUM & LIMING MATERIALS":{"Calcium Carbonate (CaCO3)":null,"Calcium Carbonate Equivalent (CaCO3)":null,"Magnesium Carbonate (MgCO3)":null,"Calcium Sulfate (CaSO42H2O)":null},"waste_derived_fertilizer":"Y","micronutrient_fertilizer":"N"},"composition":{"guaranteed_analysis":{"Total Nitrogen (N)":8.0,"Available Phosphoric Acid (P2O5)":4.0,"Soluble Potash (K2O)":5.0,"Calcium (Ca)":7.0,"Magnesium (Mg)":0.7,"Sulfur (S)":3.0,"Boron (B)":0.02,"Chlorine (Cl)":null,"Cobalt (Co)":0.0005,"Copper (Cu)":0.05,"Iron (Fe)":0.1,"Manganese (Mn)":0.05,"Molybdenum (Mo)":0.0005,"Sodium (Na)":null,"Zinc (Zn)":0.05},"heavy_metals":{"Arsenic":"=5.0000","Cadmium":"=5.0000","Cobalt":"=10.0000","Mercury":"=1.0000","Molybdenum":"=10.0000","Nickel":"=15.0000","Lead":"=15.0000","Selenium":"=6.4700","Zinc":"=1000.0000"},"derived_from_raw":null,"derived_from_tokens":null},"physicochemical":{"density_kg_per_l":null,"ph":{"min":null,"max":null},"ec_ms_cm":null},"commerce":{"sku_list":[],"price_history":[]},"metadata":{"registrant":"PERFECT BLEND LLC","label_name":"PERFECT BLEND ORGANICS BIOTIC 8-4-5 SGN 150 8-4-5","wsda_reg_no":"(#1026-0015)","formulation":null,"first_seen":"2025-07-25","detail_updated_at":"2025-07-25T11:15:37Z"}}